<?xml version="1.0" encoding="utf-8"?>
<page>
	<head>
		<title>Subscriptions</title>
		<meta name="description" content="All the subscriptions owned by you"/>
	</head>
	<body>
		<header level="1">Subscriptions</header>
		<confirmations>
			<confirmation purpose="cancellation">
				<message>Are you sure you want to cancel the subscription?</message>
				<title>Cancel</title>
				<href>subscriptions/delete</href>
				<glyphicon>remove</glyphicon>
			</confirmation>
		</confirmations>
		<tables>
			<table purpose="overview">
				<headings>
					<heading>#</heading>
					<heading sort="last_update">Last update</heading>
					<heading sort="interval">Interval</heading>
					<heading sort="expression">Expression</heading>
					<heading sort="url">URL</heading>
					<heading>Content</heading>
					<heading>Options</heading>
				</headings>
			</table>
		</tables>
	</body>
</page>
